{
	"en": {
		"money": "+1 coin",
		"pay_name": "Top up",
		"loading": "Loading",
		"location": "Location",
		"pay": "Confirm payment",
		"choise_payway": "Please choose a payment method",
		"recharge_center": "Top up center",
		"recharge_platform": "Top up platform:",
		"recharge_money": "Top up amount:",
		"recharge_declar": "Statement: our company is not involved in any way with the contest or sweepstakes.",
		"reflow": "Traffic",
		"support": "Support ",
		"order_center": "Order Center",
		"order_detail": "Order Detail",
		"order_search_info": "No search result, please make sure the requirement is right.",
		"contact_us": "Contact Us",
		"Please input your order number": "Check order ID",
		"Search": "Search",
		"order_money": "Top-up amount:",
		"order_info": "Top up details:",
		"order_sn": "Order ID:",
		"order_wait_pay": "Waiting for payment",
		"order_paid": "Paid",
		"order_pay_fail": "Paid failed",
		"order_pay_cancel": "Cancel",
		"order_state_used": "Yes",
		"order_state_unused": "No",
		"order_date": "Order payment data:",
		"order_info_other": "Other illustration:",
		"order_payway": "Payment methods:",
		"order_status": "Order status:",
		"nav_home": "Plantform introduction",
		"nav_product": "Products center",
		"nav_order": "Check order",
		"nav_help": "Help center",
		"platform_pc": "PC",
		"platform_mobile": "Mobile",
		"copyright": "@2016, Nuage Times Technology Limited, All Rights Reserved",
		"nav_login": "Sign in/Sign up",
		"recharge_tips_taotaole": "NT$10= 1 Coin + Available for 1 day's Smart Cleaner VIP",
		"recharge_tips_bingo18": "NT$10= 2 Coin + Available for 1 day's Smart Cleaner VIP",
		"recharge_tips_vpn-master": "10NT$/M",
		"recharge_tips_smart-cleaner": "10NT$/Day",
		"recharge_tips_jakarta2000": "RP. 2000 = 1M VPN Master (1 free coin as a gift)",
		"nav_user_guide": "User guide"
	}
}
